candy/__init__.py
candy/candy_wrapper.py
candy_wrapper-1.0.1.dist-info/LICENSE
candy_wrapper-1.0.1.dist-info/METADATA
candy_wrapper-1.0.1.dist-info/WHEEL
candy_wrapper-1.0.1.dist-info/RECORD
