Metadata-Version: 2.1
Name: candy-wrapper
Version: 1.0.1
Summary: A "sticky" wrapper for any object, that allow other objects to be add as propeties, which can be access through the .key notation or [key] notation. To unrap the object just add () notation to the end of the function.
License: Apache 2.0
Author: daniel davee
Author-email: daniel.v.davee@gmail.com
Requires-Python: >=3.8,<4.0
Classifier: License :: Other/Proprietary License
Classifier: Programming Language :: Python :: 3
Classifier: Programming Language :: Python :: 3.8
Classifier: Programming Language :: Python :: 3.9
Classifier: Programming Language :: Python :: 3.10
Classifier: Programming Language :: Python :: 3.11
Requires-Dist: pysimplelog (>=4.0.0,<5.0.0)
Requires-Dist: yes-or-no (>=1.0.0,<2.0.0)
